setup.py
TerminalHeader.egg-info/PKG-INFO
TerminalHeader.egg-info/SOURCES.txt
TerminalHeader.egg-info/dependency_links.txt
TerminalHeader.egg-info/entry_points.txt
TerminalHeader.egg-info/top_level.txt
theader/__init__.py
theader/__main__.py
theader/etc/__init__.py
theader/jinja2/__init__.py
theader/jinja2/_compat.py
theader/jinja2/_stringdefs.py
theader/jinja2/bccache.py
theader/jinja2/compiler.py
theader/jinja2/constants.py
theader/jinja2/debug.py
theader/jinja2/defaults.py
theader/jinja2/environment.py
theader/jinja2/exceptions.py
theader/jinja2/ext.py
theader/jinja2/filters.py
theader/jinja2/lexer.py
theader/jinja2/loaders.py
theader/jinja2/meta.py
theader/jinja2/nodes.py
theader/jinja2/optimizer.py
theader/jinja2/parser.py
theader/jinja2/runtime.py
theader/jinja2/sandbox.py
theader/jinja2/tests.py
theader/jinja2/utils.py
theader/jinja2/visitor.py
theader/markupsafe/__init__.py
theader/markupsafe/_compat.py
theader/markupsafe/_constants.py
theader/markupsafe/_native.py
theader/markupsafe/tests.py
theader/template/__init__.py
theader/template/body/__init__.py
theader/template/header/__init__.py