Metadata-Version: 1.0
Name: TerminalHeader
Version: 0.32
Summary: Add File Header use Terminal
Home-page: UNKNOWN
Author: Alan Wang
Author-email: wangchengchao115@gmail.com
License: GPL
Platform: UNKNOWN
